hierarchy_transformers/__init__.py
hierarchy_transformers/plot.py
hierarchy_transformers/utils.py
hierarchy_transformers/datasets/__init__.py
hierarchy_transformers/datasets/construct.py
hierarchy_transformers/datasets/load.py
hierarchy_transformers/evaluation/__init__.py
hierarchy_transformers/evaluation/hit_eval.py
hierarchy_transformers/evaluation/metrics.py
hierarchy_transformers/evaluation/sbert_eval.py
hierarchy_transformers/evaluation/static_embed_eval.py
hierarchy_transformers/losses/__init__.py
hierarchy_transformers/losses/hit_loss.py
hierarchy_transformers/losses/hyper_cone_loss.py
hierarchy_transformers/losses/poincare_embed_loss.py
hierarchy_transformers/models/__init__.py
hierarchy_transformers/models/hierarchy_transformer/__init__.py
hierarchy_transformers/models/hierarchy_transformer/hit.py
hierarchy_transformers/models/hierarchy_transformer/hit_trainer.py
hierarchy_transformers/models/hierarchy_transformer/hyperbolic.py
hierarchy_transformers/models/static_embed/__init__.py
hierarchy_transformers/models/static_embed/poincare_embed.py
hierarchy_transformers/models/static_embed/poincare_trainer.py
hierarchy_transformers-0.1.1.dist-info/LICENSE
hierarchy_transformers-0.1.1.dist-info/METADATA
hierarchy_transformers-0.1.1.dist-info/WHEEL
hierarchy_transformers-0.1.1.dist-info/top_level.txt
hierarchy_transformers-0.1.1.dist-info/RECORD
