Metadata-Version: 2.1
Name: hierarchy_transformers
Version: 0.1.1
Summary: Language models as hierarchy encoders.
Author-email: Yuan He <yuan.he@cs.ox.ac.uk>
Maintainer-email: Yuan He <yuan.he@cs.ox.ac.uk>
License: Apache License 2.0
Project-URL: Homepage, https://krr-oxford.github.io/HierarchyTransformers/
Project-URL: Repository, https://github.com/KRR-Oxford/HierarchyTransformers
Keywords: Language Models,Transformer Encoders,Hierarchy Encoders,Hierarchy Embedding,Hyperbolic Embedding
Classifier: Programming Language :: Python :: 3.9
Classifier: Programming Language :: Python :: 3.10
Classifier: Programming Language :: Python :: 3.11
Classifier: Programming Language :: Python :: 3.12
Classifier: License :: OSI Approved :: Apache Software License
Classifier: Intended Audience :: Developers
Classifier: Intended Audience :: Science/Research
Classifier: Topic :: Scientific/Engineering :: Artificial Intelligence
Requires-Python: >=3.9
License-File: LICENSE
Requires-Dist: sentence_transformers[train]>=3.4.0.dev0
Requires-Dist: deeponto>=0.9.2
Requires-Dist: geoopt==0.5.0
Requires-Dist: scipy==1.13.1
Requires-Dist: seaborn
Provides-Extra: dev
Requires-Dist: pytest; extra == "dev"
Requires-Dist: pytest-cov; extra == "dev"
Requires-Dist: pytest-env; extra == "dev"
